markitecture/__init__.py
markitecture/__main__.py
markitecture/errors.py
markitecture/version.py
markitecture/cli/__init__.py
markitecture/cli/app.py
markitecture/cli/commands/__init__.py
markitecture/cli/commands/config.py
markitecture/cli/commands/links.py
markitecture/cli/commands/metrics.py
markitecture/cli/commands/mkdocs.py
markitecture/cli/commands/split.py
markitecture/generators/__init__.py
markitecture/generators/configs/__init__.py
markitecture/generators/configs/mintlify_json.py
markitecture/generators/configs/mkdocs_yaml.py
markitecture/metrics/__init__.py
markitecture/metrics/analyzer.py
markitecture/metrics/svg_generator.py
markitecture/metrics/badges/__init__.py
markitecture/metrics/badges/base.py
markitecture/metrics/badges/compact.py
markitecture/metrics/badges/detailed.py
markitecture/metrics/badges/minimal.py
markitecture/metrics/badges/modern.py
markitecture/metrics/badges/retro.py
markitecture/metrics/badges/shields.py
markitecture/processing/__init__.py
markitecture/processing/link_validator.py
markitecture/processing/reflink_converter.py
markitecture/processing/reflink_extractor.py
markitecture/processing/text_splitter.py
markitecture/settings/__init__.py
markitecture/settings/config.py
markitecture/settings/validators.py
markitecture/utils/__init__.py
markitecture/utils/file_handler.py
markitecture/utils/printer.py
markitecture/utils/sanitizer.py
markitecture-0.2.33.dist-info/METADATA
markitecture-0.2.33.dist-info/WHEEL
markitecture-0.2.33.dist-info/entry_points.txt
markitecture-0.2.33.dist-info/licenses/LICENSE
markitecture-0.2.33.dist-info/RECORD
