Metadata-Version: 2.4
Name: markitecture
Version: 0.2.33
Summary: Markdown tools for modular workflows and content management.
Project-URL: documentation, https://github.com/eli64s/markitecture/blob/main/README.md
Project-URL: homepage, https://github.com/eli64s/markitecture
Project-URL: repository, https://github.com/eli64s/markitecture
Author-email: Eli Salamie <egsalamie@gmail.com>
License-Expression: MIT
License-File: LICENSE
Keywords: automated-markdown,content-management,documentation-tools,intelligent-documentation,markdown-ai,markdown-link-checker,markdown-parser,markdown-splitter,markdown-tools,mkdocs,modular-docs,readme-generator,reference-links,smart-markdown
Classifier: Development Status :: 3 - Alpha
Classifier: Framework :: Pydantic
Classifier: Framework :: Pytest
Classifier: Intended Audience :: Developers
Classifier: License :: OSI Approved :: MIT License
Classifier: Operating System :: OS Independent
Classifier: Programming Language :: Python :: 3.10
Classifier: Programming Language :: Python :: 3.11
Classifier: Programming Language :: Python :: 3.12
Classifier: Programming Language :: Python :: 3.13
Classifier: Topic :: Software Development :: Documentation
Classifier: Topic :: Software Development :: Libraries
Classifier: Topic :: Software Development :: Libraries :: Python Modules
Classifier: Typing :: Typed
Requires-Python: <=3.14,>=3.10
Requires-Dist: httpx
Requires-Dist: pydantic
Requires-Dist: pydantic-settings
Requires-Dist: pyyaml
Requires-Dist: requests
Requires-Dist: rich
Requires-Dist: toml; python_full_version < '3.11'
